{
  "_fv": 39,
  "_type": "tool",
  "definition": {
    "renderType": 1,
    "texture": "moonlight_glaive",
    "customModelName": "moonlight_glaive.geo_-_converted_-_converted:default",
    "name": "Moonlight Dagger",
    "specialInfo": [],
    "creativeTab": {
      "value": "COMBAT"
    },
    "toolType": "Sword",
    "harvestLevel": 0,
    "efficiency": 0.0,
    "attackSpeed": 1.9,
    "enchantability": 12,
    "damageVsEntity": 5.5,
    "usageCount": 2100,
    "blocksAffected": [],
    "hasGlow": false,
    "repairItems": [],
    "immuneToFire": false,
    "stayInGridWhenCrafting": false,
    "damageOnCrafting": false
  }
}